pytorch_extra_mhirano/__init__.py
pytorch_extra_mhirano/experimental/__init__.py
pytorch_extra_mhirano/experimental/variance_decomposition.py
pytorch_extra_mhirano/nn/__init__.py
pytorch_extra_mhirano/nn/attention.py
pytorch_extra_mhirano/nn/loss.py
pytorch_extra_mhirano/nn/pe.py
pytorch_extra_mhirano/nn/pyramid.py
pytorch_extra_mhirano/nn/residual.py
pytorch_extra_mhirano/nn/sum.py
pytorch_extra_mhirano/version.py
pytorch_extra_mhirano-0.1.9.dist-info/LICENSE
pytorch_extra_mhirano-0.1.9.dist-info/METADATA
pytorch_extra_mhirano-0.1.9.dist-info/WHEEL
pytorch_extra_mhirano-0.1.9.dist-info/RECORD
