Metadata-Version: 2.1
Name: pytorch_extra_mhirano
Version: 0.1.9
Summary: 
License: MIT
Author: Masanori HIRANO
Author-email: masa.hirano.1996@gmail.com
Requires-Python: >=3.8,<4.0
Classifier: License :: OSI Approved :: MIT License
Classifier: Programming Language :: Python :: 3
Classifier: Programming Language :: Python :: 3.8
Classifier: Programming Language :: Python :: 3.9
Classifier: Programming Language :: Python :: 3.10
Classifier: Programming Language :: Python :: 3.11
Requires-Dist: scipy (>=1.8.1,<2.0.0)
Requires-Dist: torch (>=1.9.0,<3.0.0,!=2.0.1)
